nano_graphrag/__init__.py
nano_graphrag/_llm.py
nano_graphrag/_op.py
nano_graphrag/_splitter.py
nano_graphrag/_utils.py
nano_graphrag/base.py
nano_graphrag/graphrag.py
nano_graphrag/prompt.py
nano_graphrag/_storage/__init__.py
nano_graphrag/_storage/gdb_neo4j.py
nano_graphrag/_storage/gdb_networkx.py
nano_graphrag/_storage/kv_json.py
nano_graphrag/_storage/vdb_hnswlib.py
nano_graphrag/_storage/vdb_nanovectordb.py
nano_graphrag/entity_extraction/__init__.py
nano_graphrag/entity_extraction/extract.py
nano_graphrag/entity_extraction/metric.py
nano_graphrag/entity_extraction/module.py
tests/__init__.py
tests/test_hnsw_vector_storage.py
tests/test_neo4j_storage.py
tests/test_networkx_storage.py
tests/test_openai.py
tests/test_rag.py
tests/test_splitter.py
tests/entity_extraction/__init__.py
tests/entity_extraction/test_extract.py
tests/entity_extraction/test_metric.py
tests/entity_extraction/test_module.py
nano_graphrag-0.0.8.2.dist-info/LICENSE
nano_graphrag-0.0.8.2.dist-info/METADATA
nano_graphrag-0.0.8.2.dist-info/WHEEL
nano_graphrag-0.0.8.2.dist-info/top_level.txt
nano_graphrag-0.0.8.2.dist-info/RECORD
